AlbertUnruhUtils/__init__.py
AlbertUnruhUtils/asynchronous/__init__.py
AlbertUnruhUtils/asynchronous/ratelimit/__init__.py
AlbertUnruhUtils/asynchronous/ratelimit/server.py
AlbertUnruhUtils/config/__init__.py
AlbertUnruhUtils/config/jsonconfig.py
AlbertUnruhUtils/ratelimit/__init__.py
AlbertUnruhUtils/ratelimit/server.py
AlbertUnruhUtils/utils/__init__.py
AlbertUnruhUtils/utils/capturing.py
AlbertUnruhUtils/utils/decorator.py
AlbertUnruhUtils/utils/logger.py
AlbertUnruhUtils/utils/version.py
AlbertUnruhUtils/visual/__init__.py
AlbertUnruhUtils/visual/tex.py
AlbertUnruhUtils.py-2.3.0.dist-info/LICENSE
AlbertUnruhUtils.py-2.3.0.dist-info/METADATA
AlbertUnruhUtils.py-2.3.0.dist-info/WHEEL
AlbertUnruhUtils.py-2.3.0.dist-info/top_level.txt
AlbertUnruhUtils.py-2.3.0.dist-info/RECORD
