Metadata-Version: 2.1
Name: AlbertUnruhUtils.py
Version: 2.3.0
Summary: A collection of utils written in Python.
Home-page: https://github.com/AlbertUnruh/AlbertUnruhUtils.py
Author: AlbertUnruh
License: MIT
Project-URL: Read The Docs, https://AlbertUnruhUtilsPy.readthedocs.io
Project-URL: Issue Tracker, https://github.com/AlbertUnruh/AlbertUnruhUtils.py/issues
Project-URL: Source Code, https://github.com/AlbertUnruh/AlbertUnruhUtils.py
Keywords: albert unruh utils configuration ratelimiting sync async logging version
Classifier: Intended Audience :: Developers
Classifier: License :: OSI Approved :: MIT License
Classifier: Operating System :: OS Independent
Classifier: Programming Language :: Python :: 3
Classifier: Programming Language :: Python :: 3.9
Classifier: Programming Language :: Python :: 3.10
Classifier: Programming Language :: Python :: 3.11
Classifier: Topic :: Software Development :: Libraries
Classifier: Topic :: Software Development :: Libraries :: Python Modules
Classifier: Topic :: Utilities
Classifier: Typing :: Typed
Requires-Python: >=3.9
License-File: LICENSE
Requires-Dist: redis (~=4.3.4)
Requires-Dist: pillow (~=9.2.0)
Requires-Dist: matplotlib (~=3.6.1)
Provides-Extra: async
Requires-Dist: aioredis (~=2.0.1) ; extra == 'async'
